opssdk/__init__.py
opssdk/utils/__init__.py
opssdk-0.1.74.data/data/share/doc/codo_sdk/README.md
websdk2/__init__.py
websdk2/api_set.py
websdk2/application.py
websdk2/base_handler.py
websdk2/cache.py
websdk2/cache_context.py
websdk2/client.py
websdk2/cloud_utils.py
websdk2/configs.py
websdk2/consts.py
websdk2/db_context.py
websdk2/error.py
websdk2/fetch_coroutine.py
websdk2/jwt_token.py
websdk2/ldap.py
websdk2/logger.py
websdk2/model_utils.py
websdk2/mqhelper.py
websdk2/program.py
websdk2/salt_api.py
websdk2/sqlalchemy_pagination.py
websdk2/tools.py
websdk2/web_logs.py
websdk2/apis/__init__.py
websdk2/apis/admin_apis.py
websdk2/apis/agent_apis.py
websdk2/apis/cmdb_apis.py
websdk2/apis/kerrigan_apis.py
websdk2/apis/mgv4_apis.py
websdk2/apis/task_apis.py
websdk2/cloud/__init__.py
websdk2/cloud/qcloud_api.py
websdk2/cloud/ucloud_api.py
websdk2/utils/__init__.py
websdk2/utils/cc_crypto.py
websdk2/utils/date_format.py
websdk2/utils/pydantic_utils.py
opssdk-0.1.74.dist-info/LICENSE
opssdk-0.1.74.dist-info/METADATA
opssdk-0.1.74.dist-info/WHEEL
opssdk-0.1.74.dist-info/top_level.txt
opssdk-0.1.74.dist-info/RECORD
