Metadata-Version: 2.1
Name: opssdk
Version: 0.1.74
Summary: CODO项目的Python SDK
Home-page: https://github.com/ss1917/codo_sdk/
Author: shenshuo
Author-email: 191715030@qq.com
License: GPLv3
Keywords: ops,opencodo,devops
Platform: any
Classifier: Development Status :: 5 - Production/Stable
Classifier: Environment :: Console :: Curses
Classifier: Intended Audience :: Developers
Classifier: License :: OSI Approved :: GNU General Public License v3 (GPLv3)
Classifier: Programming Language :: Python :: 3.6
Classifier: Programming Language :: Python :: 3.7
Classifier: Programming Language :: Python :: 3.8
Classifier: Programming Language :: Python :: 3.9
Classifier: Programming Language :: Python :: 3.9
License-File: LICENSE
Requires-Dist: fire ==0.5.0
Requires-Dist: shortuuid ==1.0.11
Requires-Dist: pymysql ==0.9.3
Requires-Dist: sqlalchemy ==1.3.23
Requires-Dist: pika ==1.3.1
Requires-Dist: PyJWT ==2.0.1
Requires-Dist: requests ==2.28.2
Requires-Dist: redis ==4.5.1
Requires-Dist: tornado >=6.0
Requires-Dist: loguru >=0.6.0
Requires-Dist: cryptography ==42.0.4
Requires-Dist: ldap3 ==2.9
Requires-Dist: pydantic >=1.10.5
